{
  "$schema": "http://json.schemastore.org/template",
  "author": "AvantiBit",
  "classifications": [
    "Web",
    "Aspire",
    "Optimizely",
    "CMS"
  ],
  "identity": "AvantiBit.Optimizely.Templates.AlloyAspireScaffold",
  "name": "Optimizely Alloy Aspire Scaffold",
  "shortName": "alloy-aspire-scaffold",
  "description": "Overlay template that adds .NET Aspire 13.3 orchestration (AppHost, ServiceDefaults, YARP, shared infrastructure, EPiServer.Azure providers for distributed blob and event propagation) to an existing Optimizely CMS 13 GA Alloy project created with 'dotnet new epi-alloy-mvc' (EPiServer.Templates >= 2.0.1). Validates the project is CMS 13; does not migrate from CMS 12.",
  "defaultName": "AlloyAspireScaffold",
  "sourceName": "AlloyAspireScaffold",
  "preferNameDirectory": false,
  "tags": {
    "language": "C#",
    "type": "solution"
  },
  "symbols": {
    "instances": {
      "type": "parameter",
      "datatype": "int",
      "defaultValue": "2",
      "description": "Number of Alloy CMS instances to configure",
      "displayName": "Instance count",
      "replaces": "INSTANCE_COUNT"
    },
    "useHttps": {
      "type": "parameter",
      "datatype": "bool",
      "defaultValue": "true",
      "description": "Configure YARP and Alloy for HTTPS",
      "displayName": "Use HTTPS"
    },
    "lbStrategy": {
      "type": "parameter",
      "datatype": "choice",
      "defaultValue": "RoundRobin",
      "description": "YARP load balancing policy",
      "displayName": "Load balancing strategy",
      "replaces": "LB_STRATEGY_VALUE",
      "choices": [
        {
          "choice": "RoundRobin",
          "description": "Distribute requests evenly across instances"
        },
        {
          "choice": "Random",
          "description": "Randomly select an instance for each request"
        },
        {
          "choice": "PowerOfTwoChoices",
          "description": "Pick the least-loaded of two randomly chosen instances"
        },
        {
          "choice": "LeastRequests",
          "description": "Route to the instance with the fewest active requests"
        },
        {
          "choice": "FirstAlphabetical",
          "description": "Route to the first alphabetically ordered instance"
        }
      ]
    },
    "skipPostAction": {
      "type": "parameter",
      "datatype": "bool",
      "defaultValue": "false",
      "description": "Skip the post-creation overlay script (generates infrastructure projects only)",
      "displayName": "Skip post-action"
    }
  },
  "sources": [
    {
      "modifiers": [
        {
          "exclude": [
            "**/[Bb]in/**",
            "**/[Oo]bj/**",
            "**/.vs/**",
            "**/.vscode/**",
            "**/*.user",
            "**/*.suo"
          ]
        }
      ]
    }
  ],
  "primaryOutputs": [
    { "path": "AlloyAspireScaffold.slnx" },
    { "path": "AlloyAspireScaffold.AppHost/AlloyAspireScaffold.AppHost.csproj" },
    { "path": "AlloyAspireScaffold.ServiceDefaults/AlloyAspireScaffold.ServiceDefaults.csproj" }
  ],
  "postActions": [
    {
      "id": "overlay-alloy",
      "condition": "(!skipPostAction)",
      "description": "Overlay Aspire orchestration + EPiServer.Azure providers onto the existing CMS 13 Alloy project",
      "manualInstructions": [
        {
          "text": "Run 'pwsh -File post-setup.ps1' in the output directory to overlay Aspire onto your CMS 13 Alloy project. The script validates the project, adds ServiceDefaults + EPiServer.Azure references, wires the Azure blob and event providers to Aspire-injected connection strings, and registers the project in the .slnx."
        }
      ],
      "actionId": "3A7C4B45-1F5D-4A30-959A-51B88E82B5D2",
      "args": {
        "executable": "pwsh",
        "args": "-File post-setup.ps1",
        "redirectStandardOutput": "false",
        "redirectStandardError": "false"
      },
      "continueOnError": false
    }
  ]
}
